pyeclib_c.abi3.so
pyeclib/__init__.py
pyeclib/core.py
pyeclib/ec_iface.py
pyeclib/utils.py
pyeclib/cli/__init__.py
pyeclib/cli/__main__.py
pyeclib/cli/bench.py
pyeclib/cli/check.py
pyeclib/cli/list.py
pyeclib/cli/verify.py
pyeclib/cli/version.py
pyeclib.libs/libXorcode-pyeclib.so.1
pyeclib.libs/liberasurecode-pyeclib.so.1
pyeclib.libs/liberasurecode_rs_vand-pyeclib.so.1
pyeclib.libs/libisal-pyeclib.so.2
pyeclib.libs/libnullcode-pyeclib.so.1
pyeclib-1.7.0.dist-info/METADATA
pyeclib-1.7.0.dist-info/WHEEL
pyeclib-1.7.0.dist-info/entry_points.txt
pyeclib-1.7.0.dist-info/top_level.txt
pyeclib-1.7.0.dist-info/RECORD
pyeclib-1.7.0.dist-info/licenses/AUTHORS
pyeclib-1.7.0.dist-info/licenses/LICENSE
pyeclib-1.7.0.dist-info/licenses/LICENSE-isal
pyeclib-1.7.0.dist-info/licenses/LICENSE-liberasurecode
