Metadata-Version: 2.4
Name: pyeclib
Version: 1.7.0
Summary: This library provides a simple Python interface for implementing erasure codes.  To obtain the best possible performance, the underlying erasure code algorithms are written in C.
Author-email: Kevin Greenan <kmgreen2@gmail.com>
Maintainer-email: Tim Burke <tim.burke@gmail.com>, Kevin Greenan <kmgreen2@gmail.com>, Tushar Gohad <tusharsg@gmail.com>
License: BSD-2-Clause
Project-URL: Homepage, https://opendev.org/openstack/pyeclib
Project-URL: Bug Tracker, https://bugs.launchpad.net/pyeclib
Project-URL: Release Notes, https://opendev.org/openstack/pyeclib/src/branch/master/ChangeLog
Platform: Linux
Classifier: Development Status :: 5 - Production/Stable
Classifier: Programming Language :: Python :: 3 :: Only
Classifier: Programming Language :: Python :: 3.10
Classifier: Programming Language :: Python :: 3.11
Classifier: Programming Language :: Python :: 3.12
Classifier: Programming Language :: Python :: 3.13
Classifier: Intended Audience :: Developers
Classifier: License :: OSI Approved :: BSD License
Requires-Python: >=3.10
License-File: LICENSE
License-File: LICENSE-isal
License-File: LICENSE-liberasurecode
License-File: AUTHORS
Dynamic: license-file
